{
  "restaurants": [
    {
      "id": 1,
      "name": "AKA",
      "location": "Bangkok",
      "image": "/images/restaurant-images/aka.png",
      "description": "Japanese Yakiniku Buffet",
      "categories": ["Buffet", "Yakiniku"],
      "rating": 4.5,
      "detail-address": "123 Sukhumvit Rd, Bangkok",
      "opening-hours": "10:00 AM - 10:00 PM",
      "price-range-per-person": "800-1500 THB"
    },
    {
      "id": 2,
      "name": "FirePlace",
      "location": "Bangkok",
      "image": "/images/restaurant-images/fireplace.jpg",
      "description": "Premium steaks cooked to perfection.",
      "categories": ["Steak House", "Fine Dining"],
      "rating": 4.7,
      "detail-address": "456 Rama IX Rd, Bangkok",
      "opening-hours": "12:00 PM - 11:00 PM",
      "price-range-per-person": "1500-3000 THB"
    },
    {
      "id": 3,
      "name": "Ministery of Crabs",
      "location": "Bangkok",
      "image": "/images/restaurant-images/moc.jpg",
      "description": "A dining experience of fresh seafoods.",
      "categories": ["Buffet", "Yakiniku"],
      "rating": 4.3,
      "detail-address": "789 Silom Rd, Bangkok",
      "opening-hours": "11:00 AM - 10:00 PM",
      "price-range-per-person": "1000-2000 THB"
    },
    {
      "id": 4,
      "name": "After You",
      "location": "Bangkok",
      "image": "/images/restaurant-images/afteryou.jpg",
      "description": "A dining experience on the water.",
      "categories": ["Dessert", "Cafe"],
      "rating": 4.6,
      "detail-address": "101 Chao Phraya River, Bangkok",
      "opening-hours": "9:00 AM - 9:00 PM",
      "price-range-per-person": "300-600 THB"
    },
    {
      "id": 5,
      "name": "Chao Phraya Princess",
      "location": "Bangkok",
      "image": "/images/restaurant-images/cruise-dinner1.webp",
      "description": "A dining experience on the water.",
      "categories": ["Cruise Dinner", "Buffet"],
      "rating": 4.8,
      "detail-address": "Chao Phraya River, Bangkok",
      "opening-hours": "6:00 PM - 10:00 PM",
      "price-range-per-person": "1500-2500 THB"
    },
    {
      "id": 6,
      "name": "Maruumi",
      "location": "Bangkok",
      "image": "/images/restaurant-images/maruumi.jpg",
      "description": "A dining experience on the water.",
      "categories": ["Omakase"],
      "rating": 4.9,
      "detail-address": "456 Riverside, Bangkok",
      "opening-hours": "12:00 PM - 10:00 PM",
      "price-range-per-person": "3000-5000 THB"
    },
    {
      "id": 7,
      "name": "Cruise Dinner Bliss",
      "location": "Phuket",
      "image": "/images/restaurant-images/cruise-dinner1.webp",
      "description": "A dining experience on the water.",
      "categories": ["Buffet", "Yakiniku"],
      "rating": 4.2,
      "detail-address": "Phuket Marina, Phuket",
      "opening-hours": "6:00 PM - 10:00 PM",
      "price-range-per-person": "1200-2000 THB"
    },
    {
      "id": 8,
      "name": "Cruise Dinner Bliss",
      "location": "Phuket",
      "image": "/images/restaurant-images/cruise-dinner1.webp",
      "description": "A dining experience on the water.",
      "categories": ["Buffet", "Yakiniku"],
      "rating": 4.2,
      "detail-address": "Phuket Marina, Phuket",
      "opening-hours": "6:00 PM - 10:00 PM",
      "price-range-per-person": "1200-2000 THB"
    },
    {
      "id": 9,
      "name": "Cruise Dinner Bliss",
      "location": "Phuket",
      "image": "/images/restaurant-images/cruise-dinner1.webp",
      "description": "A dining experience on the water.",
      "categories": ["Buffet", "Yakiniku"],
      "rating": 4.2,
      "detail-address": "Phuket Marina, Phuket",
      "opening-hours": "6:00 PM - 10:00 PM",
      "price-range-per-person": "1200-2000 THB"
    },
    {
      "id": 10,
      "name": "Cruise Dinner Bliss",
      "location": "Phuket",
      "image": "/images/restaurant-images/cruise-dinner1.webp",
      "description": "A dining experience on the water.",
      "categories": ["Buffet", "Yakiniku"],
      "rating": 4.2,
      "detail-address": "Phuket Marina, Phuket",
      "opening-hours": "6:00 PM - 10:00 PM",
      "price-range-per-person": "1200-2000 THB"
    },
    {
      "id": 11,
      "name": "Cruise Dinner Bliss",
      "location": "Phuket",
      "image": "/images/restaurant-images/cruise-dinner1.webp",
      "description": "A dining experience on the water.",
      "categories": ["Buffet", "Yakiniku"],
      "rating": 4.2,
      "detail-address": "Phuket Marina, Phuket",
      "opening-hours": "6:00 PM - 10:00 PM",
      "price-range-per-person": "1200-2000 THB"
    },
    {
      "id": 12,
      "name": "Cruise Dinner Bliss",
      "location": "Phuket",
      "image": "/images/restaurant-images/cruise-dinner1.webp",
      "description": "A dining experience on the water.",
      "categories": ["Buffet", "Yakiniku"],
      "rating": 4.2,
      "detail-address": "Phuket Marina, Phuket",
      "opening-hours": "6:00 PM - 10:00 PM",
      "price-range-per-person": "1200-2000 THB"
    },
    {
      "id": 13,
      "name": "Cruise Dinner Bliss",
      "location": "Phuket",
      "image": "/images/restaurant-images/cruise-dinner1.webp",
      "description": "A dining experience on the water.",
      "categories": ["Buffet", "Yakiniku"],
      "rating": 4.2,
      "detail-address": "Phuket Marina, Phuket",
      "opening-hours": "6:00 PM - 10:00 PM",
      "price-range-per-person": "1200-2000 THB"
    },
    {
      "id": 14,
      "name": "Cruise Dinner Bliss",
      "location": "Phuket",
      "image": "/images/restaurant-images/cruise-dinner1.webp",
      "description": "A dining experience on the water.",
      "categories": ["Buffet", "Yakiniku"],
      "rating": 4.2,
      "detail-address": "Phuket Marina, Phuket",
      "opening-hours": "6:00 PM - 10:00 PM",
      "price-range-per-person": "1200-2000 THB"
    },
    {
      "id": 15,
      "name": "Cruise Dinner Bliss",
      "location": "Phuket",
      "image": "/images/restaurant-images/cruise-dinner1.webp",
      "description": "A dining experience on the water.",
      "categories": ["Buffet", "Yakiniku"],
      "rating": 4.2,
      "detail-address": "Phuket Marina, Phuket",
      "opening-hours": "6:00 PM - 10:00 PM",
      "price-range-per-person": "1200-2000 THB"
    }
  ]
}
